cluster_optimizer/__init__.py
cluster_optimizer-0.0.2.dist-info/LICENSE
cluster_optimizer-0.0.2.dist-info/METADATA
cluster_optimizer-0.0.2.dist-info/WHEEL
cluster_optimizer-0.0.2.dist-info/top_level.txt
cluster_optimizer-0.0.2.dist-info/RECORD
