Metadata-Version: 2.1
Name: cluster_optimizer
Version: 0.0.2
Summary: A GridSearchCV like object for clustering in sklearn
Author-email: "A. Karwath" <cluster_opimizer@karwath.org>
License: MIT License
Project-URL: Homepage, https://github.com/athro/ClusterOptimizer
Keywords: sklearn,cluster,gridsearch
Classifier: License :: OSI Approved :: MIT License
Classifier: Programming Language :: Python
Classifier: Programming Language :: Python :: 3
Requires-Python: >=3.9
License-File: LICENSE
Requires-Dist: scikit-learn
Requires-Dist: pandas
